RestIFindPy-0.0.5.dist-info/METADATA
RestIFindPy-0.0.5.dist-info/RECORD
RestIFindPy-0.0.5.dist-info/WHEEL
RestIFindPy-0.0.5.dist-info/top_level.txt
direstplus/__init__.py
direstplus/config.py
direstplus/exceptions.py
direstplus/ifind.py
direstplus/ifind/__init__.py
direstplus/ifind/api.py
direstplus/ifind/exceptions.py
direstplus/ifind/invoke.py
