Metadata-Version: 2.1
Name: RestIFindPy
Version: 0.0.5
Summary: 基于Restplus实现同花顺iFinD接口分布式调用
Home-page: https://github.com/DataIntegrationAlliance/RestIFindPy
Author: MG
Author-email: mmmaaaggg@163.com
License: UNKNOWN
Platform: UNKNOWN
Classifier: Programming Language :: Python :: 3 :: Only
Classifier: Programming Language :: Python :: 3.5
Classifier: Programming Language :: Python :: 3.6
Classifier: Programming Language :: Python :: 3.7
Classifier: License :: OSI Approved :: MIT License
Classifier: Development Status :: 5 - Production/Stable
Classifier: Environment :: No Input/Output (Daemon)
Classifier: Intended Audience :: Developers
Classifier: Natural Language :: Chinese (Simplified)
Classifier: Topic :: Software Development
Requires-Python: >=3.5
Requires-Dist: flask-restplus (>=0.11.0)
Requires-Dist: pandas (>=0.23.0)
Requires-Dist: requests (>=2.19.1)
